submodulegraph.py
submodulegraph-1.0.0.dist-info/LICENSE
submodulegraph-1.0.0.dist-info/METADATA
submodulegraph-1.0.0.dist-info/WHEEL
submodulegraph-1.0.0.dist-info/entry_points.txt
submodulegraph-1.0.0.dist-info/top_level.txt
submodulegraph-1.0.0.dist-info/RECORD
