Metadata-Version: 2.1
Name: submodulegraph
Version: 1.0.0
Summary: Visualize Git Submodule Graphs
Home-page: https://github.com/bacox/submodule-graph
Author: Bart Cox
Author-email: bartcox93@gmail.com
License: UNKNOWN
Platform: UNKNOWN
Classifier: Programming Language :: Python :: 3
Classifier: License :: OSI Approved :: MIT License
Classifier: Operating System :: OS Independent
Requires-Dist: click
Requires-Dist: pydot
Requires-Dist: configparser
